LICENSE
MANIFEST.in
README.rst
requirements.txt
setup.py
NeuroDynamics.egg-info/PKG-INFO
NeuroDynamics.egg-info/SOURCES.txt
NeuroDynamics.egg-info/dependency_links.txt
NeuroDynamics.egg-info/requires.txt
NeuroDynamics.egg-info/top_level.txt
brainpy/__init__.py
brainpy/inputs.py
brainpy/measure.py
brainpy/profile.py
brainpy/running.py
brainpy/connectivity/__init__.py
brainpy/connectivity/base.py
brainpy/connectivity/formater.py
brainpy/connectivity/methods.py
brainpy/core_system/__init__.py
brainpy/core_system/base_objects.py
brainpy/core_system/constants.py
brainpy/core_system/network.py
brainpy/core_system/neurons.py
brainpy/core_system/runner.py
brainpy/core_system/synapses.py
brainpy/core_system/types.py
brainpy/dynamics/__init__.py
brainpy/dynamics/analyst.py
brainpy/integration/__init__.py
brainpy/integration/diff_equation.py
brainpy/integration/integrator.py
brainpy/integration/sympy_tools.py
brainpy/numpy/__init__.py
brainpy/numpy/linalg.py
brainpy/numpy/random.py
brainpy/numpy/_backends/__init__.py
brainpy/numpy/_backends/cupy.py
brainpy/numpy/_backends/jax.py
brainpy/numpy/_backends/numba.py
brainpy/numpy/_backends/numpy.py
brainpy/tools/__init__.py
brainpy/tools/ast2code.py
brainpy/tools/codes.py
brainpy/tools/dicts.py
brainpy/tools/functions.py
brainpy/tools/logger.py
brainpy/visualization/__init__.py
docs/Makefile
docs/conf.py
docs/index.rst
docs/make.bat
docs/apis/changelog.rst
docs/apis/core.rst
docs/apis/neurons.rst
docs/apis/synapses.rst
docs/apis/usage_of_inputfactory.py
docs/apis/usage_of_utils_connect.py
docs/apis/usage_of_utils_connect.rst
docs/apis/utils.rst
docs/apis/.ipynb_checkpoints/usage_of_utils_connect-checkpoint.py
docs/apis/.ipynb_checkpoints/utils_input_factory-checkpoint.py
docs/apis/_autosummary/npbrain.core.Euler_method.rst
docs/apis/_autosummary/npbrain.core.Heun_method.rst
docs/apis/_autosummary/npbrain.core.Milstein_dfree_Ito.rst
docs/apis/_autosummary/npbrain.core.Milstein_dfree_Stra.rst
docs/apis/_autosummary/npbrain.core.backward_Euler.rst
docs/apis/_autosummary/npbrain.core.firing_rate.rst
docs/apis/_autosummary/npbrain.core.format_delay.rst
docs/apis/_autosummary/npbrain.core.format_geometry.rst
