Metadata-Version: 1.2
Name: NeuroDynamics
Version: 0.1.1
Summary: NeuroDynamics: A Just-In-Time compilation approach for neuronal dynamics simulation.
Home-page: https://github.com/PKU-NIP-Lab/BrainPy
Author: Chaoming Wang
Author-email: adaduo@outlook.com
License: UNKNOWN
Keywords: computational neuroscience
Platform: UNKNOWN
Classifier: Intended Audience :: Science/Research
Classifier: Natural Language :: English
Classifier: Operating System :: OS Independent
Classifier: Programming Language :: Python
Classifier: Programming Language :: Python :: 3
Classifier: Topic :: Scientific/Engineering :: Bio-Informatics
Requires-Python: >=3.5
